pmlauncher/__init__.py
pmlauncher/mdownloader.py
pmlauncher/mevent.py
pmlauncher/minecraft.py
pmlauncher/mlaunch.py
pmlauncher/mlaunchoption.py
pmlauncher/mlibrary.py
pmlauncher/mlogin.py
pmlauncher/mnative.py
pmlauncher/mprofile.py
pmlauncher/mprofileinfo.py
pmlauncher/pml.py
pmlauncher-0.0.3.dist-info/METADATA
pmlauncher-0.0.3.dist-info/WHEEL
pmlauncher-0.0.3.dist-info/top_level.txt
pmlauncher-0.0.3.dist-info/RECORD
