Metadata-Version: 2.1
Name: pmlauncher
Version: 0.0.3
Summary: crossplatform Python Minecraft Launcher support forge and all version
Home-page: https://github.com/AlphaBs/pml
Author: ksi123456ab
Author-email: ksi123456ab@naver.com
License: non commercial
Keywords: minecraft,launcher
Platform: UNKNOWN
Classifier: Programming Language :: Python :: 3.0
Classifier: Programming Language :: Python :: 3.1
Classifier: Programming Language :: Python :: 3.2
Classifier: Programming Language :: Python :: 3.3
Classifier: Programming Language :: Python :: 3.4
Classifier: Programming Language :: Python :: 3.5
Classifier: Programming Language :: Python :: 3.6
Classifier: Programming Language :: Python :: 3.7
Classifier: Programming Language :: Python :: 3.8
Classifier: Topic :: Games/Entertainment
Requires-Python: >=3
Requires-Dist: requests
